{
  "mihindukulasooriya": 22,
  "rankoth": 20,
  "siththi": 20,
  "dilrukshi": 20,
  "seiyadu": 19,
  "balasooriya": 17,
  "priyankara": 17,
  "anusha": 17,
  "abeysinghe": 17,
  "mohommadu": 16,
  "ameen": 16,
  "hettiarachchige": 16,
  "gayan": 16,
  "subasinghe": 16,
  "chamara": 16,
  "ahamad": 16,
  "kamal": 16,
  "nisar": 15,
  "asanka": 15,
  "madusanka": 15,
  "rasika": 15,
  "nilanka": 15,
  "ranjani": 15,
  "dinesh": 14,
  "sri": 14,
  "aruna": 14,
  "senanayaka": 14,
  "kondasinghe": 14,
  "nishshanka": 14,
  "segu": 13,
  "edirisinghe": 13,
  "shanthi": 13,
  "ashoka": 13,
  "sameera": 13,
  "pichchai": 13,
  "gamlath": 13,
  "lakshman": 13,
  "nuwan": 12,
  "mahesh": 12,
  "sumith": 12,
  "sujeewa": 12,
  "wickrama": 12,
  "anne": 12,
  "dilani": 12,
  "premasiri": 12,
  "chanaka": 12,
  "naseer": 11,
  "pedi": 11,
  "dasanayake": 11,
  "ambagahage": 11,
  "abdeen": 11,
  "niluka": 11,
  "poruthotage": 11,
  "jamaldeen": 11,
  "amila": 11,
  "karunanayaka": 11,
  "senadhipathi": 11,
  "muhandiramlage": 11,
  "sifan": 11,
  "nimesha": 11,
  "thisera": 10,
  "jayamanna": 10,
  "bandaralage": 10,
  "palitha": 10,
  "sandamali": 10,
  "jayasooriya": 10,
  "sudarshani": 10,
  "suresh": 10,
  "lalith": 10,
  "sandaruwan": 10,
  "sujith": 10,
  "nandana": 10,
  "chamila": 10,
  "sewwandi": 10,
  "shyamali": 10,
  "mohideen": 10,
  "deepal": 10,
  "buddhika": 10,
  "kachchakaduge": 10,
  "shanika": 10,
  "harsha": 10,
  "malkanthi": 9,
  "nalin": 9,
  "manoj": 9,
  "nilmini": 9,
  "naidelage": 9,
  "laxman": 9,
  "abesingha": 9,
  "sanath": 9,
  "ishara": 9,
  "rodrigo": 9,
  "jayasiri": 9,
  "kuranage": 9,
  "rohitha": 9,
  "sriyani": 9,
  "muhaideen": 9,
  "chandima": 9,
  "kader": 9,
  "anil": 9,
  "ranpati": 9,
  "madhuwanthi": 9,
  "shirani": 9,
  "prabhath": 9,
  "thanthrige": 9,
  "chithra": 9,
  "anwar": 8,
  "pulle": 8,
  "nisansala": 8,
  "neina": 8,
  "upali": 8,
  "devage": 8,
  "ameer": 8,
  "lal": 8,
  "wijethunga": 8,
  "latheef": 8,
  "nirmala": 8,
  "fonseka": 8,
  "chinthaka": 8,
  "abeyrathna": 8,
  "randeniya": 8,
  "rahuman": 8,
  "ismath": 8,
  "mangalika": 8,
  "mallawa": 8,
  "dias": 8,
  "riswan": 8,
  "nasar": 8,
  "senadheera": 8,
  "krishantha": 8,
  "sandya": 8,
  "ishan": 8,
  "nadeesha": 8,
  "walimuni": 8,
  "inoka": 7,
  "akila": 7,
  "thamel": 7,
  "isuru": 7,
  "kusumalatha": 7,
  "seinul": 7,
  "nihal": 7,
  "rohana": 7,
  "kumarasiri": 7,
  "priyangika": 7,
  "randunu": 7,
  "muththalage": 7,
  "banu": 7,
  "iresha": 7,
  "supun": 7,
  "casim": 7,
  "sulthan": 7,
  "samsudeen": 7,
  "chathurika": 7,
  "samarathunga": 7,
  "sagara": 7,
  "dhanushka": 7,
  "hamid": 7,
  "athula": 7,
  "kurukulasooriya": 7,
  "swarna": 7,
  "rasheed": 7,
  "wijesooriya": 7,
  "anas": 7,
  "badurdeen": 7,
  "lekamlage": 7,
  "kavinda": 7,
  "rasak": 7,
  "hitihamillage": 7,
  "jagath": 6,
  "meera": 6,
  "thambi": 6,
  "sugath": 6,
  "khan": 6,
  "sisira": 6,
  "dabare": 6,
  "pathum": 6,
  "janith": 6,
  "pulhiri": 6,
  "sudath": 6,
  "sooriyahetti": 6,
  "abubakkar": 6,
  "niranjan": 6,
  "ramees": 6,
  "ranathunga": 6,
  "duminda": 6,
  "malani": 6,
  "manel": 6,
  "priyalal": 6,
  "lahiru": 6,
  "jayaweera": 6,
  "wickramanayaka": 6,
  "seinulabdeen": 6,
  "kamil": 6,
  "ansar": 6,
  "chakrawarthige": 6,
  "wijesundara": 6,
  "kalu": 6,
  "mohottige": 6,
  "heshan": 6,
  "senevirathna": 6,
  "dharmasiri": 6,
  "udayangani": 6,
  "hemantha": 6,
  "mahinda": 6,
  "acharige": 6,
  "kahanda": 6,
  "jayathilaka": 6,
  "haseem": 6,
  "majeed": 6,
  "eranga": 6,
  "damith": 6,
  "dinusha": 6,
  "ravindra": 6,
  "asath": 6,
  "sandun": 6,
  "semasinghe": 5,
  "marian": 5,
  "kasim": 5,
  "haja": 5,
  "musammil": 5,
  "begam": 5,
  "dilip": 5,
  "rukman": 5,
  "akbar": 5,
  "ilham": 5,
  "abuthahir": 5,
  "niyas": 5,
  "jayamaha": 5,
  "jabbar": 5,
  "madawala": 5,
  "nonis": 5,
  "kasun": 5,
  "renuka": 5,
  "indrani": 5,
  "premalal": 5,
  "nadeeka": 5,
  "kithsiri": 5,
  "ratnayake": 5,
  "edward": 5,
  "prasath": 5,
  "thawfeek": 5,
  "kanthi": 5,
  "atheek": 5,
  "mahamalage": 5,
  "sunimal": 5,
  "thusitha": 5,
  "muththu": 5,
  "nageswaran": 5,
  "thilini": 5,
  "irugal": 5,
  "vimukthi": 5,
  "kaluarachchi": 5,
  "mohan": 5,
  "rangana": 5,
  "rathugamage": 5,
  "muthunayaka": 5,
  "udugampalage": 5,
  "saleem": 5,
  "fareed": 5,
  "usan": 5,
  "subhashini": 5,
  "aslam": 5,
  "faruk": 5,
  "kusum": 5,
  "gunathilaka": 5,
  "komala": 5,
  "sinhala": 5,
  "thilak": 5,
  "maduranga": 5,
  "weththasinghe": 5,
  "nalinda": 5,
  "nayomi": 5,
  "paththinige": 5,
  "priya": 5,
  "stanley": 5,
  "hitihami": 5,
  "niranjala": 5,
  "deepthi": 5,
  "sanjaya": 5,
  "amrin": 5,
  "sujani": 5,
  "shashikala": 5,
  "sachini": 5,
  "saibu": 5,
  "abusali": 5,
  "isadeen": 5,
  "fairoos": 5,
  "chandrawathi": 5,
  "dushmantha": 5,
  "sandeepa": 5,
  "srimal": 5,
  "wijesekara": 5,
  "rukshan": 5,
  "pillai": 4,
  "naseem": 4,
  "paththima": 4,
  "ummu": 4,
  "haleem": 4,
  "asees": 4,
  "jawfar": 4,
  "begum": 4,
  "nawas": 4,
  "weerakoon": 4,
  "lakshika": 4,
  "kalyani": 4,
  "siril": 4,
  "salihu": 4,
  "suranjan": 4,
  "farook": 4,
  "guruge": 4,
  "nelka": 4,
  "pathma": 4,
  "askar": 4,
  "yapa": 4,
  "riyas": 4,
  "asha": 4,
  "dharmasena": 4,
  "wimalasena": 4,
  "gihan": 4,
  "malala": 4,
  "pathiraja": 4,
  "kasthuri": 4,
  "rathna": 4,
  "henayalage": 4,
  "liyanaralalage": 4,
  "udeni": 4,
  "wijesiri": 4,
  "siraj": 4,
  "warnakula": 4,
  "dilini": 4,
  "samith": 4,
  "chandrasiri": 4,
  "roy": 4,
  "premathilaka": 4,
  "loku": 4,
  "nalaka": 4,
  "udayasiri": 4,
  "hapan": 4,
  "katunayakage": 4,
  "wickramapala": 4,
  "kadupitige": 4,
  "dinithi": 4,
  "irshad": 4,
  "thahir": 4,
  "silmiya": 4,
  "rasmin": 4,
  "habeeb": 4,
  "faisal": 4,
  "nasir": 4,
  "naleem": 4,
  "saheed": 4,
  "mathara": 4,
  "rifai": 4,
  "haider": 4,
  "kumuduni": 4,
  "mursid": 4,
  "jerad": 4,
  "wahab": 4,
  "mihirani": 4,
  "anuruddha": 4,
  "douglas": 4,
  "priyangani": 4,
  "nandasiri": 4,
  "sriya": 4,
  "rumesh": 4,
  "siriwardhana": 4,
  "tharanga": 4,
  "rifas": 4,
  "gunawardhana": 4,
  "wijendra": 4,
  "ravi": 4,
  "eranda": 4,
  "piyasena": 4,
  "siyam": 4,
  "peter": 4,
  "miranda": 4,
  "disna": 4,
  "manori": 4,
  "samaranayaka": 4,
  "weligamage": 4,
  "rifan": 4,
  "risana": 4,
  "jesmin": 4,
  "nasurdeen": 4,
  "prince": 4,
  "noordeen": 4,
  "ponnawila": 4,
  "dharmarathna": 4,
  "sajeewani": 4,
  "madhumali": 4,
  "perumbadage": 4,
  "ariyadasa": 4,
  "samarappulige": 4,
  "husein": 4,
  "jayampathi": 4,
  "randika": 4,
  "rex": 4,
  "hasitha": 4,
  "nipun": 4,
  "sunethra": 4,
  "siyambalapitiyage": 4,
  "amara": 4,
  "dushan": 4,
  "geetha": 4,
  "jawahir": 4,
  "raja": 4,
  "risvi": 3,
  "kiyas": 3,
  "imran": 3,
  "barakath": 3,
  "rasidu": 3,
  "kelum": 3,
  "safran": 3,
  "siyad": 3,
  "himi": 3,
  "sukri": 3,
  "thanuja": 3,
  "qasim": 3,
  "basir": 3,
  "nagur": 3,
  "kadar": 3,
  "nahur": 3,
  "kareem": 3,
  "abdulla": 3,
  "najath": 3,
  "sathsarani": 3,
  "kalladi": 3,
  "anula": 3,
  "thommage": 3,
  "baduge": 3,
  "baseer": 3,
  "kurugamage": 3,
  "christy": 3,
  "amanulla": 3,
  "george": 3,
  "sanoon": 3,
  "pasil": 3,
  "sinhanayake": 3,
  "manikkuge": 3,
  "kusumawathi": 3,
  "nayana": 3,
  "champika": 3,
  "fasil": 3,
  "kalugamage": 3,
  "deepika": 3,
  "sarifu": 3,
  "sooriya": 3,
  "alfred": 3,
  "weerakkodi": 3,
  "godage": 3,
  "welikala": 3,
  "abbas": 3,
  "ange": 3,
  "wijjapathi": 3,
  "wijedasa": 3,
  "nawarathna": 3,
  "wijjapathiyalage": 3,
  "lionel": 3,
  "hemamali": 3,
  "piyasiri": 3,
  "meragal": 3,
  "waduge": 3,
  "kuttige": 3,
  "hamim": 3,
  "thuwan": 3,
  "kanchana": 3,
  "umar": 3,
  "athige": 3,
  "dhanapala": 3,
  "nalawansha": 3,
  "korala": 3,
  "keerthi": 3,
  "ponnamperuma": 3,
  "palakuttige": 3,
  "ranjanee": 3,
  "deekiri": 3,
  "kamani": 3,
  "nelson": 3,
  "wijenayaka": 3,
  "hapu": 3,
  "kuruppu": 3,
  "mahalekam": 3,
  "manju": 3,
  "pathmasiri": 3,
  "ethige": 3,
  "asela": 3,
  "wijeratne": 3,
  "jayathissa": 3,
  "padma": 3,
  "emmanuel": 3,
  "pattivilage": 3,
  "ivon": 3,
  "manchanayaka": 3,
  "thilakanayake": 3,
  "mahawaththage": 3,
  "joy": 3,
  "mahabaduge": 3,
  "asraf": 3,
  "dilantha": 3,
  "rinosa": 3,
  "maharoof": 3,
  "siyan": 3,
  "thaslim": 3,
  "hasim": 3,
  "ranwalage": 3,
  "sehu": 3,
  "sajahan": 3,
  "muni": 3,
  "nawsad": 3,
  "paruk": 3,
  "sajan": 3,
  "azan": 3,
  "sajath": 3,
  "samad": 3,
  "thushan": 3,
  "parana": 3,
  "beevi": 3,
  "thambiliyagodage": 3,
  "nisthar": 3,
  "hussain": 3,
  "nilusha": 3,
  "rani": 3,
  "safrin": 3,
  "handun": 3,
  "hapuarachchige": 3,
  "shelton": 3,
  "sakunthala": 3,
  "thilakasiri": 3,
  "somasiri": 3,
  "weerasekara": 3,
  "muthugala": 3,
  "bandula": 3,
  "kovilage": 3,
  "sumedha": 3,
  "kandasami": 3,
  "madhushika": 3,
  "perumbuli": 3,
  "ayesha": 3,
  "samudra": 3,
  "achala": 3,
  "wilbert": 3,
  "kadawatha": 3,
  "rismiya": 3,
  "muthukuda": 3,
  "siripala": 3,
  "nasik": 3,
  "charith": 3,
  "ilangarathna": 3,
  "mahendran": 3,
  "wijekumar": 3,
  "faleel": 3,
  "hafeel": 3,
  "alan": 3,
  "christopher": 3,
  "madarasingha": 3,
  "ibunu": 3,
  "ramanayaka": 3,
  "saumya": 3,
  "bhagya": 3,
  "ramesh": 3,
  "wijebandara": 3,
  "jayage": 3,
  "swarnalatha": 3,
  "ajantha": 3,
  "kumaragama": 3,
  "samson": 3,
  "hansa": 3,
  "kingsly": 3,
  "silmaguruge": 3,
  "sasika": 3,
  "irangani": 3,
  "jayalal": 3,
  "ruwanthi": 3,
  "amarosige": 3,
  "sheran": 3,
  "alexander": 3,
  "sumali": 3,
  "noyel": 3,
  "masewge": 3,
  "manthilaka": 3,
  "michael": 3,
  "paththamperuma": 3,
  "faslan": 3,
  "nuska": 3,
  "nasrin": 3,
  "rafi": 3,
  "pasan": 3,
  "sareena": 3,
  "nisan": 3,
  "dileepa": 3,
  "maddumage": 3,
  "sugandhika": 3,
  "himali": 3,
  "chandradipathilayage": 3,
  "wimal": 3,
  "ariyarathne": 3,
  "peramuna": 3,
  "wijayanthi": 3,
  "biyatris": 3,
  "sivanadan": 3,
  "muditha": 3,
  "christin": 3,
  "irfan": 3,
  "koswaththa": 3,
  "pasindu": 3,
  "manike": 2,
  "pedidurayalage": 2,
  "muthuporuthotage": 2,
  "somasundaram": 2,
  "thammitage": 2,
  "lafeer": 2,
  "cadar": 2,
  "jaleel": 2,
  "safnas": 2,
  "amir": 2,
  "kalam": 2,
  "nilfa": 2,
  "kafoor": 2,
  "saththar": 2,
  "pakeer": 2,
  "hamdun": 2,
  "minhas": 2,
  "rahim": 2,
  "rizwan": 2,
  "hapeel": 2,
  "vaseela": 2,
  "muthalif": 2,
  "kutti": 2,
  "jorge": 2,
  "swarnamali": 2,
  "irshath": 2,
  "gulam": 2,
  "nimmi": 2,
  "marsalin": 2,
  "rashmi": 2,
  "elizabeth": 2,
  "yusuf": 2,
  "rishab": 2,
  "saliya": 2,
  "thakshila": 2,
  "baby": 2,
  "dananjana": 2,
  "jawfer": 2,
  "mawjood": 2,
  "jalal": 2,
  "waseem": 2,
  "brito": 2,
  "offar": 2,
  "safeer": 2,
  "salam": 2,
  "janab": 2,
  "mahumudu": 2,
  "aly": 2,
  "wishwanath": 2,
  "kabeer": 2,
  "fahim": 2,
  "mohidin": 2,
  "nijam": 2,
  "naleen": 2,
  "junaideen": 2,
  "maheshika": 2,
  "lowe": 2,
  "bastian": 2,
  "sadath": 2,
  "frank": 2,
  "sisitha": 2,
  "haroon": 2,
  "ponweera": 2,
  "hettige": 2,
  "gurusinghe": 2,
  "sumudu": 2,
  "pichche": 2,
  "rizvi": 2,
  "lekam": 2,
  "kapoor": 2,
  "jabir": 2,
  "pethum": 2,
  "maha": 2,
  "parook": 2,
  "indra": 2,
  "ruvina": 2,
  "farwin": 2,
  "hasri": 2,
  "sadakathulla": 2,
  "muhandiram": 2,
  "chamali": 2,
  "perummuni": 2,
  "haris": 2,
  "kalimuththu": 2,
  "edirimannage": 2,
  "lakshmi": 2,
  "namal": 2,
  "ramachandran": 2,
  "vincent": 2,
  "ujitha": 2,
  "deshapriya": 2,
  "winson": 2,
  "wilfred": 2,
  "panikka": 2,
  "tikiri": 2,
  "basith": 2,
  "bakir": 2,
  "ben": 2,
  "wawa": 2,
  "weerasena": 2,
  "baiya": 2,
  "karunathilaka": 2,
  "lanka": 2,
  "haluge": 2,
  "wimalasiri": 2,
  "ilandari": 2,
  "kulawathi": 2,
  "mapa": 2,
  "jayasena": 2,
  "kosala": 2,
  "hathweni": 2,
  "ubhayasena": 2,
  "wickramasooriya": 2,
  "payagalage": 2,
  "palihawadana": 2,
  "wadugedara": 2,
  "imihami": 2,
  "nalika": 2,
  "panambara": 2,
  "nilamelage": 2,
  "roopa": 2,
  "anjana": 2,
  "janaki": 2,
  "chandrasena": 2,
  "justin": 2,
  "leena": 2,
  "fayas": 2,
  "anuradha": 2,
  "bacha": 2,
  "rismi": 2,
  "diyagu": 2,
  "nadika": 2,
  "rilwan": 2,
  "muthumali": 2,
  "zeinul": 2,
  "abulhuda": 2,
  "arif": 2,
  "dimuthu": 2,
  "baranaduge": 2,
  "robis": 2,
  "salim": 2,
  "selvam": 2,
  "gardi": 2,
  "katulanda": 2,
  "ilangakoon": 2,
  "safiya": 2,
  "shiyabudeen": 2,
  "edwin": 2,
  "vimalraj": 2,
  "mervin": 2,
  "reginold": 2,
  "rahumathulla": 2,
  "sasikumar": 2,
  "nadar": 2,
  "dharmadasa": 2,
  "wagapedige": 2,
  "jute": 2,
  "kapila": 2,
  "mandalawalli": 2,
  "thammahetti": 2,
  "kantha": 2,
  "ahnaf": 2,
  "mawathage": 2,
  "wijaya": 2,
  "egoda": 2,
  "witharanage": 2,
  "ponnakuttige": 2,
  "shehan": 2,
  "milroy": 2,
  "nihar": 2,
  "duwage": 2,
  "hadhi": 2,
  "piyal": 2,
  "rathnasekara": 2,
  "dilki": 2,
  "rangajeewa": 2,
  "sahudhu": 2,
  "uwais": 2,
  "kure": 2,
  "jesudasan": 2,
  "nicholas": 2,
  "gunasekara": 2,
  "ghouz": 2,
  "yoosuf": 2,
  "raseem": 2,
  "susith": 2,
  "soma": 2,
  "morin": 2,
  "balapuwaduge": 2,
  "tharushi": 2,
  "kaushalya": 2,
  "murugaiya": 2,
  "nazar": 2,
  "bodiya": 2,
  "mahagamage": 2,
  "primal": 2,
  "weda": 2,
  "philip": 2,
  "modara": 2,
  "suren": 2,
  "menike": 2,
  "mallika": 2,
  "siwanthi": 2,
  "dewamunige": 2,
  "karunapedi": 2,
  "viskam": 2,
  "padmini": 2,
  "chaya": 2,
  "na": 2,
  "induru": 2,
  "muthumudalige": 2,
  "obinamunige": 2,
  "katugampala": 2,
  "uduvila": 2,
  "mudiyanse": 2,
  "vijesingha": 2,
  "appu": 2,
  "sujee": 2,
  "jayashantha": 2,
  "imalka": 2,
  "lalantha": 2,
  "sudesh": 2,
  "mahathelge": 2,
  "rajika": 2,
  "amarapathi": 2,
  "lathika": 2,
  "chandralatha": 2,
  "rendage": 2,
  "asiri": 2,
  "weerasiri": 2,
  "dilruk": 2,
  "kammella": 2,
  "ederage": 2,
  "ranmuthu": 2,
  "yasmin": 2,
  "galgamuge": 2,
  "milan": 2,
  "sudeera": 2,
  "pinthu": 2,
  "alex": 2,
  "livera": 2,
  "imihamilage": 2,
  "menaka": 2,
  "polgampala": 2,
  "pubudu": 2,
  "kattakuttige": 2,
  "churchill": 2,
  "mulacharige": 2,
  "kewage": 2,
  "wathumulla": 2,
  "coorera": 2,
  "goviwanshage": 2,
  "adappage": 2,
  "dolahamunige": 2,
  "malith": 2,
  "ramyalatha": 2,
  "danansooriya": 2,
  "srinath": 2,
  "reegan": 2,
  "hansani": 2,
  "wahid": 2,
  "mahadurage": 2,
  "adambarage": 2,
  "sujatha": 2,
  "ramsan": 2,
  "nisam": 2,
  "ifnas": 2,
  "anvardeen": 2,
  "sifaniya": 2,
  "hafil": 2,
  "farsan": 2,
  "sahaya": 2,
  "safi": 2,
  "sajitha": 2,
  "sabra": 2,
  "ifthikar": 2,
  "aminudeen": 2,
  "sajida": 2,
  "farween": 2,
  "sahan": 2,
  "ayubkarn": 2,
  "jemeel": 2,
  "sandakelum": 2,
  "mansur": 2,
  "arafath": 2,
  "mumthaj": 2,
  "linda": 2,
  "chamod": 2,
  "terinsan": 2,
  "sahabdeen": 2,
  "mahir": 2,
  "shalitha": 2,
  "ranaweera": 2,
  "arshad": 2,
  "yasar": 2,
  "udagama": 2,
  "hasara": 2,
  "prakash": 2,
  "hirushan": 2,
  "asarudeen": 2,
  "sulfikar": 2,
  "asura": 2,
  "calista": 2,
  "aluth": 2,
  "nawfar": 2,
  "habaragoda": 2,
  "aswar": 2,
  "fasli": 2,
  "kanisius": 2,
  "hakeem": 2,
  "sami": 2,
  "shafee": 2,
  "majid": 2,
  "sunanda": 2,
  "nuhuman": 2,
  "nadee": 2,
  "shalaka": 2,
  "fasran": 2,
  "neel": 2,
  "riswi": 2,
  "huda": 2,
  "charuka": 2,
  "alikhan": 2,
  "widanelage": 2,
  "sriyalatha": 2,
  "mafas": 2,
  "anusiya": 2,
  "daluwaththage": 2,
  "sunitha": 2,
  "sudaraka": 2,
  "jahubar": 2,
  "rinas": 2,
  "tharaka": 2,
  "himaya": 2,
  "masud": 2,
  "madhawa": 2,
  "almedha": 2,
  "madana": 2,
  "ahsan": 2,
  "navodya": 2,
  "anaston": 2,
  "diksan": 2,
  "kassali": 2,
  "hisham": 2,
  "sanjeewanee": 2,
  "sakalasooriya": 2,
  "niroshanee": 2,
  "deddugodagamage": 2,
  "gayashan": 2,
  "nilakshi": 2,
  "wattage": 2,
  "biyanwilage": 2,
  "hemachandra": 2,
  "palihana": 2,
  "prabodha": 2,
  "dewaraja": 2,
  "palliya": 2,
  "keerthirathna": 2,
  "sumanasiri": 2,
  "kulasuriya": 2,
  "karunadasa": 2,
  "dharmapriya": 2,
  "lesli": 2,
  "theres": 2,
  "hashini": 2,
  "rasangika": 2,
  "mery": 2,
  "matilda": 2,
  "singha": 2,
  "abeywickrama": 2,
  "kalamulla": 2,
  "maleesha": 2,
  "manage": 2,
  "satharasingha": 2,
  "sahid": 2,
  "munawwara": 2,
  "victor": 2,
  "subhash": 2,
  "sarojani": 2,
  "sheik": 2,
  "lawrence": 2,
  "naflan": 2,
  "batugahage": 2,
  "bamunuarachchi": 2,
  "masood": 2,
  "premadasa": 2,
  "welathanthrige": 2,
  "arumage": 2,
  "nandini": 2,
  "pille": 2,
  "paris": 2,
  "rameena": 2,
  "madappuli": 2,
  "rajeshwari": 2,
  "susil": 2,
  "costa": 2,
  "udeshika": 2,
  "amali": 2,
  "shyamalee": 2,
  "ganithayalage": 2,
  "wanasingha": 2,
  "moolachcharilage": 2,
  "athapaththu": 2,
  "nekathige": 2,
  "weththige": 2,
  "krishnan": 2,
  "hewawasam": 2,
  "udara": 2,
  "rathnasiri": 2,
  "abeysekara": 2,
  "mercius": 2,
  "kurukula": 2,
  "natalia": 2,
  "ashani": 2,
  "roshen": 2,
  "madhuka": 2,
  "lasanthi": 2,
  "dulanjali": 2,
  "wanniarachchi": 2,
  "shalini": 2,
  "walisinghe": 2,
  "akurana": 2,
  "kapuge": 2,
  "chethana": 2,
  "ranamuka": 2,
  "patrick": 2,
  "merril": 2,
  "premakumara": 2,
  "madurapperuma": 2,
  "colin": 2,
  "miriyam": 2,
  "melani": 2,
  "greshan": 2,
  "anuththara": 2,
  "thirimanna": 2,
  "paul": 2,
  "singhabahu": 2,
  "abhayavikrama": 2,
  "wedaralalage": 2,
  "sarathchandra": 1,
  "vackrama": 1,
  "siwamathi": 1,
  "seelan": 1,
  "jenat": 1,
  "verlina": 1,
  "saduni": 1,
  "anupa": 1,
  "ilma": 1,
  "lafnas": 1,
  "sanchaka": 1,
  "dedunu": 1,
  "sellan": 1,
  "bosco": 1,
  "neelika": 1,
  "namshan": 1,
  "assam": 1,
  "munaweera": 1,
  "badurdin": 1,
  "madeena": 1,
  "seinab": 1,
  "siyal": 1,
  "ikmail": 1,
  "aisa": 1,
  "nilupa": 1,
  "risilikan": 1,
  "hiti": 1,
  "pushpalatha": 1,
  "manamendralage": 1,
  "rajawardhana": 1,
  "nagamuththu": 1,
  "maaladhi": 1,
  "nihsadini": 1,
  "sada": 1,
  "salika": 1,
  "abukaneefa": 1,
  "meeralebbe": 1,
  "jeseer": 1,
  "waleeth": 1,
  "behum": 1,
  "sulpiya": 1,
  "saleemkhan": 1,
  "insiraf": 1,
  "rajiya": 1,
  "raseen": 1,
  "finosdeen": 1,
  "ajas": 1,
  "naveeth": 1,
  "farijan": 1,
  "nawfer": 1,
  "rafaideen": 1,
  "thajudeen": 1,
  "gomez": 1,
  "segusikkandar": 1,
  "safeez": 1,
  "natheer": 1,
  "hasnafar": 1,
  "hakim": 1,
  "huseen": 1,
  "sabnas": 1,
  "ibbraheem": 1,
  "pasiliya": 1,
  "palidi": 1,
  "bari": 1,
  "fahir": 1,
  "jeseema": 1,
  "hai": 1,
  "shakeena": 1,
  "hayas": 1,
  "wadu": 1,
  "hairul": 1,
  "sakariya": 1,
  "aseema": 1,
  "arham": 1,
  "dawdu": 1,
  "bulathsinghe": 1,
  "jayalakmali": 1,
  "jeyaraj": 1,
  "langeshwaree": 1,
  "kulathilaka": 1,
  "diran": 1,
  "siththijeseema": 1,
  "laththeeb": 1,
  "resmina": 1,
  "indisami": 1,
  "murugesu": 1,
  "murugan": 1,
  "alima": 1,
  "razakkia": 1,
  "ominaduni": 1,
  "parakrama": 1,
  "sakina": 1,
  "bilani": 1,
  "preethikumari": 1,
  "galkanda": 1,
  "kumarasamipillei": 1,
  "kalehi": 1,
  "selvi": 1,
  "mujeena": 1,
  "naliyer": 1,
  "sinnappulige": 1,
  "norman": 1,
  "aziz": 1,
  "rathini": 1,
  "nagoda": 1,
  "mukpil": 1,
  "govinnage": 1,
  "musawwar": 1,
  "pukoya": 1,
  "kadira": 1,
  "jayamini": 1,
  "rifka": 1,
  "madhushantha": 1,
  "wahideen": 1,
  "chafas": 1,
  "raslan": 1,
  "ripnaas": 1,
  "mubasheer": 1,
  "muhammadali": 1,
  "pawsiya": 1,
  "padige": 1,
  "josapin": 1,
  "kosali": 1,
  "ladamuththu": 1,
  "ramachandramoorthi": 1,
  "ukusdeen": 1,
  "nimitha": 1,
  "raththinam": 1,
  "yakupitiyage": 1,
  "aslal": 1,
  "sharmila": 1,
  "kather": 1,
  "mirashahib": 1,
  "parhan": 1,
  "muneepa": 1,
  "ripkan": 1,
  "nafas": 1,
  "pattan": 1,
  "widana": 1,
  "masahira": 1,
  "pirooz": 1,
  "ranaveerage": 1,
  "kuraisiya": 1,
  "obina": 1,
  "subajini": 1,
  "hamdoon": 1,
  "fazi": 1,
  "mikes": 1,
  "afthar": 1,
  "chamidu": 1,
  "lebbai": 1,
  "pramith": 1,
  "thariq": 1,
  "rev": 1,
  "stavira": 1,
  "emalian": 1,
  "mitlant": 1,
  "sekan": 1,
  "nawpal": 1,
  "jesta": 1,
  "ubaidulla": 1,
  "jinna": 1,
  "jaufer": 1,
  "sashee": 1,
  "ayub": 1,
  "paleel": 1,
  "rilmiyas": 1,
  "kiriliyanage": 1,
  "niyuman": 1,
  "alstor": 1,
  "minhaj": 1,
  "dombawalage": 1,
  "anastri": 1,
  "pizel": 1,
  "diyomi": 1,
  "minfas": 1,
  "asankuddoos": 1,
  "bedwewa": 1,
  "thera": 1,
  "vaas": 1,
  "weerapurage": 1,
  "hafarath": 1,
  "razuldeen": 1,
  "andrew": 1,
  "lewwai": 1,
  "paseel": 1,
  "saheer": 1,
  "seynul": 1,
  "manzil": 1,
  "mufariz": 1,
  "weerasin": 1,
  "palamandadige": 1,
  "jesper": 1,
  "cricentos": 1,
  "unais": 1,
  "ilyas": 1,
  "maheesan": 1,
  "asmi": 1,
  "naufar": 1,
  "hamish": 1,
  "jokinu": 1,
  "purkan": 1,
  "ansah": 1,
  "naufith": 1,
  "raasik": 1,
  "amirkhan": 1,
  "makeen": 1,
  "mooseen": 1,
  "najimudeen": 1,
  "hudubudeen": 1,
  "sahulhameethu": 1,
  "wahap": 1,
  "hakkib": 1,
  "fahri": 1,
  "paronas": 1,
  "lelwala": 1,
  "sumeeri": 1,
  "viduranga": 1,
  "samanmali": 1,
  "almudeen": 1,
  "danapalage": 1,
  "sawindra": 1,
  "sewmini": 1,
  "siliyange": 1,
  "kumarasoorijan": 1,
  "pavin": 1,
  "samadhi": 1,
  "maduhansi": 1,
  "kalidu": 1,
  "puwad": 1,
  "buhul": 1,
  "suhudip": 1,
  "jipri": 1,
  "kuthupus": 1,
  "yoonus": 1,
  "bakeer": 1,
  "nasmin": 1,
  "kodippili": 1,
  "maryal": 1,
  "ifam": 1,
  "naim": 1,
  "pairus": 1,
  "busuli": 1,
  "hafis": 1,
  "gapoor": 1,
  "rapees": 1,
  "zaiyad": 1,
  "shihan": 1,
  "nafath": 1,
  "rikas": 1,
  "najiuddin": 1,
  "sabaragamu": 1,
  "aswarhan": 1,
  "thirimadura": 1,
  "wenura": 1,
  "milhaj": 1,
  "ramanadan": 1,
  "thamban": 1,
  "jhon": 1,
  "gemunu": 1,
  "mafan": 1,
  "malik": 1,
  "kaleel": 1,
  "gabriel": 1,
  "ronglin": 1,
  "sabrasdeen": 1,
  "divulage": 1,
  "muthuwahandi": 1,
  "rapiel": 1,
  "noorullakan": 1,
  "suharid": 1,
  "yaseer": 1,
  "vernal": 1,
  "wonhard": 1,
  "liyanadurage": 1,
  "prabesh": 1,
  "padmakumara": 1,
  "iwan": 1,
  "shaheel": 1,
  "mahdun": 1,
  "mahil": 1,
  "kafil": 1,
  "jameel": 1,
  "faseem": 1,
  "subadinee": 1,
  "fazal": 1,
  "padicoralalage": 1,
  "sapwan": 1,
  "sivaperumal": 1,
  "vasudevi": 1,
  "rohis": 1,
  "farzan": 1,
  "suhaibudeen": 1,
  "navusath": 1,
  "rupus": 1,
  "yasir": 1,
  "fasrin": 1,
  "nifraz": 1,
  "basan": 1,
  "roomi": 1,
  "irpan": 1,
  "kirige": 1,
  "hamsa": 1,
  "hafsa": 1,
  "hidayathulla": 1,
  "fawkan": 1,
  "rameez": 1,
  "mufeen": 1,
  "kiriella": 1,
  "parameswaran": 1,
  "kamsa": 1,
  "rislan": 1,
  "niran": 1,
  "cadir": 1,
  "faiser": 1,
  "nizam": 1,
  "marceline": 1,
  "abuhaneepa": 1,
  "manikkam": 1,
  "kanpali": 1,
  "firnas": 1,
  "paseen": 1,
  "rejeen": 1,
  "sugandi": 1,
  "gangani": 1,
  "sadik": 1,
  "asfana": 1,
  "ferwin": 1,
  "yoosup": 1,
  "rihas": 1,
  "husni": 1,
  "razak": 1,
  "nagoor": 1,
  "nisha": 1,
  "wipula": 1,
  "pahmi": 1,
  "muthumenika": 1,
  "parththamil": 1,
  "puhalendi": 1,
  "jeenath": 1,
  "dilrukshan": 1,
  "navidu": 1,
  "samira": 1,
  "nachchiyyage": 1,
  "magret": 1,
  "thaha": 1,
  "namayiwayam": 1,
  "jinadari": 1,
  "thausadhu": 1,
  "rifkhan": 1,
  "mahagoda": 1,
  "risvideen": 1,
  "murukaiyah": 1,
  "muhaman": 1,
  "walangu": 1,
  "saraswathi": 1,
  "polwaththe": 1,
  "udari": 1,
  "poonathan": 1,
  "sathees": 1,
  "surendra": 1,
  "saheeka": 1,
  "mohamath": 1,
  "sijath": 1,
  "pajurdeen": 1,
  "darmes": 1,
  "savuru": 1,
  "aksar": 1,
  "risni": 1,
  "rushda": 1,
  "yunpikoon": 1,
  "jemil": 1,
  "wappumaraikkar": 1,
  "ponnin": 1,
  "alponsina": 1,
  "nuwanthika": 1,
  "reeta": 1,
  "dhananjani": 1,
  "fuwad": 1,
  "noorul": 1,
  "awahidha": 1,
  "asthik": 1,
  "ira": 1,
  "majinus": 1,
  "dilsam": 1,
  "foujan": 1,
  "majinoon": 1,
  "maskari": 1,
  "jahan": 1,
  "thomas": 1,
  "telesta": 1,
  "manohary": 1,
  "janika": 1,
  "kalai": 1,
  "chelvi": 1,
  "landa": 1,
  "niroshini": 1,
  "godiyana": 1,
  "muththaiya": 1,
  "lawanya": 1,
  "sruthi": 1,
  "wellana": 1,
  "bammanne": 1,
  "hasni": 1,
  "malporu": 1,
  "hafees": 1,
  "prasankha": 1,
  "nishandani": 1,
  "farsad": 1,
  "haseeb": 1,
  "ijilan": 1,
  "rihan": 1,
  "fajeer": 1,
  "pilasius": 1,
  "munap": 1,
  "naufeek": 1,
  "nisal": 1,
  "ahana": 1,
  "menidher": 1,
  "lukas": 1,
  "iyoobkhan": 1,
  "amjathkhan": 1,
  "faris": 1,
  "suwailim": 1,
  "sifradh": 1,
  "dewaguruge": 1,
  "raththinajothi": 1,
  "kubarajani": 1,
  "kristhoper": 1,
  "rusanthan": 1,
  "ravuththa": 1,
  "aseera": 1,
  "jamiul": 1,
  "ghassali": 1,
  "muhammudhu": 1,
  "tharsika": 1,
  "ajwad": 1,
  "asakan": 1,
  "firaz": 1,
  "kichil": 1,
  "salif": 1,
  "hafeez": 1,
  "benjamin": 1,
  "thambiliyana": 1,
  "dinuka": 1,
  "munige": 1,
  "anisra": 1,
  "mahumoodu": 1,
  "dodangoda": 1,
  "senadhira": 1,
  "dumunnage": 1,
  "vishmi": 1,
  "rameskhan": 1,
  "pajeer": 1,
  "wanni": 1,
  "achchi": 1,
  "wepola": 1,
  "ambagahakandage": 1,
  "jeyinulabtheen": 1,
  "alkimas": 1,
  "walpola": 1,
  "chanchala": 1,
  "rusdhy": 1,
  "godihenagamage": 1,
  "bonnet": 1,
  "ishak": 1,
  "dinaya": 1,
  "lalani": 1,
  "ramsi": 1,
  "sakeel": 1,
  "mehthab": 1,
  "afthaf": 1,
  "mahbub": 1,
  "simak": 1,
  "nusman": 1,
  "duleeka": 1,
  "lapayadurayalage": 1,
  "anandavardhana": 1,
  "nalir": 1,
  "neelappage": 1,
  "gate": 1,
  "irene": 1,
  "casmiyarge": 1,
  "leroi": 1,
  "pinto": 1,
  "wijayabandara": 1,
  "jaya": 1,
  "dilashal": 1,
  "elmo": 1,
  "malavi": 1,
  "prasadika": 1,
  "athaudaththi": 1,
  "thalammaharage": 1,
  "chandanee": 1,
  "suranganee": 1,
  "weerayalage": 1,
  "rukunayaka": 1,
  "violat": 1,
  "antanat": 1,
  "wickramathilaka": 1,
  "suraj": 1,
  "mainaththuge": 1,
  "mahapatabandige": 1,
  "nirmalee": 1,
  "bodhinayakage": 1,
  "diyunugal": 1,
  "purage": 1,
  "korallage": 1,
  "obada": 1,
  "warnage": 1,
  "anuranga": 1,
  "weragoda": 1,
  "shobha": 1,
  "krishni": 1,
  "ihagama": 1,
  "uduwarage": 1,
  "dingiri": 1,
  "madhavi": 1,
  "ganesalingam": 1,
  "thilan": 1,
  "henry": 1,
  "palipanage": 1,
  "luxman": 1,
  "vonali": 1,
  "kidmini": 1,
  "wasthu": 1,
  "nawanjali": 1,
  "ginigerathne": 1,
  "kiringoda": 1,
  "menikralage": 1,
  "sirithunga": 1,
  "pallewela": 1,
  "koongaha": 1,
  "dawundage": 1,
  "rajini": 1,
  "muthugalpedi": 1,
  "makevita": 1,
  "rosana": 1,
  "rooparathne": 1,
  "chandhi": 1,
  "kalukumara": 1,
  "indrarathna": 1,
  "agostheenu": 1,
  "dayananda": 1,
  "wijayasinghelage": 1,
  "sirisena": 1,
  "indrananda": 1,
  "mainakkuge": 1,
  "pallegedara": 1,
  "gabadage": 1,
  "bodhi": 1,
  "sudharma": 1,
  "mihidu": 1,
  "densil": 1,
  "nissanga": 1,
  "joe": 1,
  "vernon": 1,
  "premarathna": 1,
  "hewapelage": 1,
  "harisan": 1,
  "yashodha": 1,
  "nethanjaya": 1,
  "upadissa": 1,
  "chandradasa": 1,
  "kudagammanage": 1,
  "dangallage": 1,
  "kahandagamage": 1,
  "jawaran": 1,
  "chamalee": 1,
  "ranhari": 1,
  "aatheege": 1,
  "kumudumali": 1,
  "elle": 1,
  "gallaththa": 1,
  "medagedara": 1,
  "dushyanthi": 1,
  "paragoda": 1,
  "karunasundara": 1,
  "nanediri": 1,
  "tumbaliyaddalage": 1,
  "buwaneka": 1,
  "siththarage": 1,
  "muthuporu": 1,
  "thotage": 1,
  "linkan": 1,
  "yasapala": 1,
  "kentley": 1,
  "mekala": 1,
  "sesathpura": 1,
  "daham": 1,
  "diyalagoda": 1,
  "podimanika": 1,
  "hemalatha": 1,
  "liyanapedi": 1,
  "sethuwa": 1,
  "manthreerathna": 1,
  "piyarathna": 1,
  "richard": 1,
  "pallayalage": 1,
  "senavirathne": 1,
  "horathal": 1,
  "patabandi": 1,
  "dileesha": 1,
  "dehigolle": 1,
  "mahalekamlage": 1,
  "ruwanmali": 1,
  "sandareka": 1,
  "weerasangiliyalage": 1,
  "mannapperuma": 1,
  "subodha": 1,
  "kumarabanda": 1,
  "surasena": 1,
  "ilangandassa": 1,
  "pin": 1,
  "panikkiyalage": 1,
  "kulathunga": 1,
  "kirimudiyanse": 1,
  "dulanga": 1,
  "aseeskan": 1,
  "kisokan": 1,
  "thotahewage": 1,
  "edirimuni": 1,
  "balagalla": 1,
  "kanthilatha": 1,
  "pliny": 1,
  "juliet": 1,
  "wasim": 1,
  "akram": 1,
  "maujud": 1,
  "thambaru": 1,
  "dharmaraj": 1,
  "alahan": 1,
  "jane": 1,
  "paksha": 1,
  "leela": 1,
  "nandanee": 1,
  "bulath": 1,
  "bulathsinhalage": 1,
  "anuruddika": 1,
  "wijethilaka": 1,
  "sritharan": 1,
  "samanpriya": 1,
  "vee": 1,
  "badde": 1,
  "fasloon": 1,
  "faseer": 1,
  "hamadiya": 1,
  "panu": 1,
  "jiffry": 1,
  "jihas": 1,
  "faisar": 1,
  "abubacker": 1,
  "azeem": 1,
  "ashmila": 1,
  "hanzul": 1,
  "raufiya": 1,
  "thabodani": 1,
  "thirunavapragasam": 1,
  "susikala": 1,
  "velu": 1,
  "sithi": 1,
  "fathrun": 1,
  "sanoos": 1,
  "juwasir": 1,
  "samiyas": 1,
  "seyad": 1,
  "charles": 1,
  "franklin": 1,
  "mathaw": 1,
  "kushan": 1,
  "gayasri": 1,
  "madurawalage": 1,
  "ovitigala": 1,
  "nawalage": 1,
  "apsara": 1,
  "ranuri": 1,
  "upendra": 1,
  "semsan": 1,
  "jacinta": 1,
  "evprasia": 1,
  "rathnakumara": 1,
  "kankanamdurage": 1,
  "kumarasamy": 1,
  "pasupathinathan": 1,
  "rijaji": 1,
  "situge": 1,
  "wattoru": 1,
  "udenika": 1,
  "seenathmal": 1,
  "raihanaththu": 1,
  "beewi": 1,
  "nawfiya": 1,
  "faththih": 1,
  "baduria": 1,
  "badurul": 1,
  "miskan": 1,
  "nadija": 1,
  "chakravarthalage": 1,
  "sanjeevan": 1,
  "nimna": 1,
  "sithum": 1,
  "kandegoda": 1,
  "komange": 1,
  "mahanthe": 1,
  "vilha": 1,
  "visurumana": 1,
  "munaf": 1,
  "nasima": 1,
  "muhiru": 1,
  "fsan": 1,
  "jenut": 1,
  "induja": 1,
  "mahubum": 1,
  "shandhyani": 1,
  "seldin": 1,
  "miskin": 1,
  "inosha": 1,
  "daranagama": 1,
  "parami": 1,
  "lanuhewage": 1,
  "piyumi": 1,
  "mahagalgamuge": 1,
  "muththuveeran": 1,
  "nallarakku": 1,
  "parthiban": 1,
  "pussewala": 1,
  "udiri": 1,
  "appuwaduge": 1,
  "askia": 1,
  "wasamge": 1,
  "merley": 1,
  "puvaneswaran": 1,
  "punchimanike": 1,
  "sirimadurage": 1,
  "mahindapala": 1,
  "fazlan": 1,
  "noor": 1,
  "weliwaththage": 1,
  "muththalib": 1,
  "nipraz": 1,
  "nakif": 1,
  "savahir": 1,
  "niyaz": 1,
  "bannana": 1,
  "nilar": 1,
  "nasuda": 1,
  "wazira": 1,
  "sirida": 1,
  "maheez": 1,
  "asarun": 1,
  "farees": 1,
  "mujibar": 1,
  "risa": 1,
  "nirupa": 1,
  "anees": 1,
  "denisperan": 1,
  "jipson": 1,
  "indumathi": 1,
  "sayambu": 1,
  "sudamuhadin": 1,
  "maseeda": 1,
  "thasnima": 1,
  "farhath": 1,
  "nadira": 1,
  "sembalingam": 1,
  "wensaslas": 1,
  "lingeshwaran": 1,
  "vances": 1,
  "laws": 1,
  "donnie": 1,
  "srilal": 1,
  "sumaiya": 1,
  "indrajith": 1,
  "thellambura": 1,
  "padmasiri": 1,
  "rajapu": 1,
  "jawad": 1,
  "girigoris": 1,
  "pillage": 1,
  "thenuwara": 1,
  "pabasara": 1,
  "sadarathnage": 1,
  "thajun": 1,
  "pitiduwagamage": 1,
  "kaliyugawaradhan": 1,
  "vanigakulasekara": 1,
  "mussammin": 1,
  "muthumarasinghe": 1,
  "hapuarachi": 1,
  "sudusinghe": 1,
  "rappiyal": 1,
  "erandi": 1,
  "ajmal": 1,
  "sarjoon": 1,
  "fathumma": 1,
  "isurumani": 1,
  "jaufar": 1,
  "de-kumar": 1,
  "ahraf": 1,
  "wal": 1,
  "kathiresan": 1,
  "lamil": 1,
  "althaf": 1,
  "sirapdeen": 1,
  "valimunige": 1,
  "viniston": 1,
  "game": 1,
  "rifaz": 1,
  "donald": 1,
  "priyawasana": 1,
  "muthukumarana": 1,
  "riyasath": 1,
  "abulhasan": 1,
  "warisa": 1,
  "junaith": 1,
  "jasil": 1,
  "gafoor": 1,
  "navasdeen": 1,
  "nilupul": 1,
  "pahir": 1,
  "janzil": 1,
  "nakan": 1,
  "banuraj": 1,
  "maddemagedara": 1,
  "nidahansi": 1,
  "jayawickrama": 1,
  "inamul": 1,
  "nihardeen": 1,
  "thewar": 1,
  "horadagoda": 1,
  "pathmini": 1,
  "japarulla": 1,
  "athulasiri": 1,
  "nayanananda": 1,
  "sasmir": 1,
  "walter": 1,
  "athugal": 1,
  "kamazy": 1,
  "kalandar": 1,
  "rankiri": 1,
  "upasena": 1,
  "darmathissa": 1,
  "mindada": 1,
  "karmigan": 1,
  "lokumudali": 1,
  "jafrik": 1,
  "eventhi": 1,
  "junidu": 1,
  "insaf": 1,
  "kanapathi": 1,
  "parameshwari": 1,
  "danson": 1,
  "clancy": 1,
  "wasan": 1,
  "nosmin": 1,
  "safkan": 1,
  "shanmugam": 1,
  "amma": 1,
  "adam": 1,
  "sanuardeen": 1,
  "akbardeen": 1,
  "aflal": 1,
  "archunan": 1,
  "pushparani": 1,
  "asgar": 1,
  "roomee": 1,
  "quddoos": 1,
  "fawsul": 1,
  "mihilaldin": 1,
  "zahir": 1,
  "amasha": 1,
  "lakshini": 1,
  "nona": 1,
  "afthal": 1,
  "kananke": 1,
  "barnat": 1,
  "aswini": 1,
  "malwalage": 1,
  "rajagopal": 1,
  "sankunni": 1,
  "piyona": 1,
  "sweisina": 1,
  "soosmithani": 1,
  "hangsika": 1,
  "immanuvel": 1,
  "alagaraththinam": 1,
  "josephine": 1,
  "imakulet": 1,
  "gnanasekaram": 1,
  "isabella": 1,
  "pesneruwe": 1,
  "chalani": 1,
  "cooray": 1,
  "ramanathan": 1,
  "usha": 1,
  "mubarath": 1,
  "hasmir": 1,
  "yahiya": 1,
  "alagar": 1,
  "denida": 1,
  "harna": 1,
  "siyadha": 1,
  "nijab": 1,
  "nisadi": 1,
  "farid": 1,
  "pasmina": 1,
  "sareef": 1,
  "afroz": 1,
  "ayyan": 1,
  "zuha": 1,
  "zeinam": 1,
  "sameem": 1,
  "saliq": 1,
  "abuhanifa": 1,
  "jaslas": 1,
  "baihakki": 1,
  "nifasa": 1,
  "hafsaniya": 1,
  "nirmin": 1,
  "anosha": 1,
  "halahakoan": 1,
  "halloluwa": 1,
  "sandunika": 1,
  "thinipity": 1,
  "abhilashini": 1,
  "vishal": 1,
  "bage": 1,
  "faseeha": 1,
  "naleer": 1,
  "muthuthanthrige": 1,
  "ijas": 1,
  "parihari": 1,
  "faizul": 1,
  "thilangani": 1,
  "giniwalage": 1,
  "mahadevan": 1,
  "vishnukanth": 1,
  "illiyas": 1,
  "munasinha": 1,
  "daniel": 1,
  "prensis": 1,
  "jesu": 1,
  "sabeer": 1,
  "selladore": 1,
  "thawfik": 1,
  "aboobakkar": 1,
  "aminudhin": 1,
  "haidar": 1,
  "asvi": 1,
  "paaththi": 1,
  "dinsiya": 1,
  "rabbu": 1,
  "bisrul": 1,
  "devarajige": 1,
  "meerasa": 1,
  "amitha": 1,
  "sahara": 1,
  "mudalihamige": 1,
  "peragam": 1,
  "arachilage": 1,
  "thalpathawadana": 1,
  "vijaya": 1,
  "velayutham": 1,
  "manna": 1,
  "marakkala": 1,
  "marinkoone": 1,
  "nifla": 1,
  "moses": 1,
  "punya": 1,
  "rathnasami": 1,
  "sivanesan": 1,
  "sarges": 1,
  "safana": 1,
  "winigrida": 1,
  "navaratne": 1,
  "kamardeen": 1,
  "misraj": 1,
  "rabbani": 1,
  "maseeh": 1,
  "shiham": 1,
  "singan": 1,
  "samsul": 1,
  "shahum": 1,
  "hamdan": 1,
  "saribdeen": 1,
  "seid": 1,
  "meda": 1,
  "sawfan": 1,
  "askeen": 1,
  "jeewaka": 1,
  "kuraira": 1,
  "hasam": 1,
  "arus": 1,
  "ajuwath": 1,
  "ofoor": 1,
  "pushparaj": 1,
  "safeen": 1,
  "afridi": 1,
  "iflal": 1,
  "lafir": 1,
  "maupir": 1,
  "shakir": 1,
  "sajaf": 1,
  "wasam": 1,
  "faridhu": 1,
  "maharuf": 1,
  "rakhitha": 1,
  "mahendranathan": 1,
  "selvakumar": 1,
  "thayyoob": 1,
  "mujahidullah": 1,
  "nafees": 1,
  "safarulla": 1,
  "riyal": 1,
  "thastheek": 1,
  "sandanam": 1,
  "rasidh": 1,
  "rifraas": 1,
  "muharris": 1,
  "nilamdeen": 1,
  "nusky": 1,
  "praveen": 1,
  "fayaj": 1,
  "nasra": 1,
  "nilufar": 1,
  "jamalddin": 1,
  "lifty": 1,
  "saamila": 1,
  "sisee": 1,
  "gannoruwe": 1,
  "singaratnam": 1,
  "kathiravelu": 1,
  "cyril": 1,
  "nishamdeen": 1,
  "rahmy": 1,
  "salma": 1,
  "issidhowar": 1,
  "lio": 1,
  "kuinton": 1,
  "balraj": 1,
  "thameem": 1,
  "nizar": 1,
  "niroy": 1,
  "sarma": 1,
  "kaalingage": 1,
  "jeris": 1,
  "ranasinha": 1,
  "ameefa": 1,
  "vijeshantha": 1,
  "vithanaralalage": 1,
  "virajith": 1,
  "dhamiyantha": 1,
  "nohoth": 1,
  "heelle": 1,
  "dhanaseeli": 1,
  "marasinhage": 1,
  "nan": 1,
  "nelsan": 1,
  "shahmy": 1,
  "hayathu": 1,
  "museen": 1,
  "thusil": 1,
  "caderthambi": 1,
  "fastral": 1,
  "bandupriya": 1,
  "krawage": 1,
  "randilu": 1,
  "piyumantha": 1,
  "minneripitige": 1,
  "priyavi": 1,
  "rapiralage": 1,
  "sooriyasekara": 1,
  "plishiyan": 1,
  "kaangane": 1,
  "kaushika": 1,
  "nidurshan": 1,
  "lakmi": 1,
  "uresha": 1,
  "salgadu": 1,
  "ramani": 1,
  "rotney": 1,
  "thissa": 1,
  "telesper": 1,
  "ashen": 1,
  "milinda": 1,
  "karunamuni": 1,
  "madampage": 1,
  "nicklan": 1,
  "tharumaraththinam": 1,
  "sugashini": 1,
  "wenaida": 1,
  "isthinige": 1,
  "chamel": 1,
  "halpawalage": 1,
  "subadra": 1,
  "kurukutu": 1,
  "isuni": 1,
  "dinushsika": 1,
  "sujamili": 1,
  "ewanthika": 1,
  "madivanan": 1,
  "munas": 1,
  "meregngnage": 1,
  "amutha": 1,
  "mirigngnage": 1,
  "rajaguru": 1,
  "thalikath": 1,
  "thibunu": 1,
  "jawper": 1,
  "arsaad": 1,
  "naseha": 1,
  "chamath": 1,
  "dawud": 1,
  "shyamdeen": 1,
  "mupina": 1,
  "sulpihar": 1,
  "naizer": 1,
  "saripu": 1,
  "rajapakshalage": 1,
  "segudaudu": 1,
  "nizamudeen": 1,
  "samrun": 1,
  "pathun": 1,
  "kumudunee": 1,
  "pawzan": 1,
  "thadchanamoorthy": 1,
  "thangawelu": 1,
  "karithasan": 1,
  "nallaselwan": 1,
  "kamaleswaran": 1,
  "welupille": 1,
  "sivapalan": 1,
  "miral": 1,
  "nawaz": 1,
  "singakkuli": 1,
  "methsiri": 1,
  "abdulkalam": 1,
  "victrisiya": 1,
  "dulip": 1,
  "asmini": 1,
  "kochchigoda": 1,
  "gunasiri": 1,
  "steevan": 1,
  "rathgama": 1,
  "napila": 1,
  "mahawedage": 1,
  "piyaseeli": 1,
  "sandarath": 1,
  "maheepala": 1,
  "yasas": 1,
  "kostha": 1,
  "rathinasingam": 1,
  "samanmalee": 1,
  "dewundara": 1,
  "sangeeth": 1,
  "haseena": 1,
  "subhashana": 1,
  "nawodani": 1,
  "faumi": 1,
  "kuruwita": 1,
  "susiri": 1,
  "lokupotha": 1,
  "rinavus": 1,
  "thejanee": 1,
  "deepanee": 1,
  "vanni": 1,
  "ariyavathi": 1,
  "romesh": 1,
  "subaratne": 1,
  "wiskam": 1,
  "ranghamige": 1,
  "sathareka": 1,
  "edirippulige": 1,
  "priyatharshini": 1,
  "kaumadi": 1,
  "lional": 1,
  "vanikanayaka": 1,
  "malhevithana": 1,
  "jinsiri": 1,
  "nandawathi": 1,
  "uthashani": 1,
  "roopasingha": 1,
  "welegama": 1,
  "wavalve": 1,
  "vijelatha": 1,
  "ananthan": 1,
  "padapenthige": 1,
  "navothika": 1,
  "hettinayaka": 1,
  "eliyanayake": 1,
  "malwadamgedara": 1,
  "silpa": 1,
  "achariya": 1,
  "warnakumara": 1,
  "or": 1,
  "aberat": 1,
  "menika": 1,
  "nilmali": 1,
  "mudunapittagedara": 1,
  "sandalanka": 1,
  "sureka": 1,
  "roopika": 1,
  "bopage": 1,
  "raththaran": 1,
  "kumuthu": 1,
  "udayarathne": 1,
  "hakmana": 1,
  "ilangathassa": 1,
  "garthiya": 1,
  "maduma": 1,
  "dodamgodage": 1,
  "darma": 1,
  "haluwannehalage": 1,
  "kuda": 1,
  "weeraman": 1,
  "vipula": 1,
  "aloka": 1,
  "punchibanda": 1,
  "dharshani": 1,
  "arangala": 1,
  "udyanganee": 1,
  "goradiya": 1,
  "nimalsiri": 1,
  "asarapullige": 1,
  "harischandra": 1,
  "dharmakeerthi": 1,
  "ottukulame": 1,
  "pungngnanantha": 1,
  "thero": 1,
  "merakalage": 1,
  "yaman": 1,
  "sapuge": 1,
  "mohattalage": 1,
  "chamintha": 1,
  "rangadipathi": 1,
  "rathnamalala": 1,
  "handuwala": 1,
  "nandhadeva": 1,
  "naithelage": 1,
  "henneheka": 1,
  "kalutharage": 1,
  "kumarihami": 1,
  "juwange": 1,
  "diluka": 1,
  "sapumal": 1,
  "thevruwan": 1,
  "keeraveli": 1,
  "nithuka": 1,
  "sandaseeli": 1,
  "vanniyasekaram": 1,
  "vedipuli": 1,
  "soumya": 1,
  "shama": 1,
  "ravindu": 1,
  "dayaratna": 1,
  "sushan": 1,
  "kahandawala": 1,
  "asanga": 1,
  "sardha": 1,
  "aidurus": 1,
  "yusupge": 1,
  "nazeer": 1,
  "punjiralage": 1,
  "shesawathee": 1,
  "rajapakshapaththirannehelage": 1,
  "hempathura": 1,
  "sarangu": 1,
  "senthuperuma": 1,
  "priyadharsanee": 1,
  "siriyawathi": 1,
  "ladduge": 1,
  "withanalage": 1,
  "chithrananda": 1,
  "sudasingha": 1,
  "riyancy": 1,
  "newton": 1,
  "hasun": 1,
  "pausul": 1,
  "rimsina": 1,
  "panapitiyage": 1,
  "podibanda": 1,
  "weeramundage": 1,
  "graciyan": 1,
  "benaragama": 1,
  "gnei": 1,
  "feroza": 1,
  "babanoor": 1,
  "sharadi": 1,
  "kevitiyagala": 1,
  "pantaliyan": 1,
  "yakdehigedara": 1,
  "suraweera": 1,
  "gonagala": 1,
  "denigamage": 1,
  "kavitha": 1,
  "ratnasinkkam": 1,
  "shasiban": 1,
  "sumanaweera": 1,
  "seetha": 1,
  "sepala": 1,
  "genova": 1,
  "salis": 1,
  "chachini": 1,
  "dogahan": 1,
  "ghnanam": 1,
  "raveendra": 1,
  "prabhashwara": 1,
  "karthik": 1,
  "esan": 1,
  "sivadarshan": 1,
  "kennedy": 1,
  "korasagoda": 1,
  "vehihenage": 1,
  "salmanul": 1,
  "faiz": 1,
  "naveen": 1,
  "wijewickrama": 1,
  "sadiqul": 1,
  "warnapura": 1,
  "shalik": 1,
  "rusmiland": 1,
  "malagammana": 1,
  "gretian": 1,
  "hikkaduge": 1,
  "prinelika": 1,
  "butlett": 1,
  "majini": 1,
  "rambukkana": 1,
  "maninkkage": 1,
  "kachchu": 1,
  "kaduge": 1,
  "alexshiyas": 1,
  "hilary": 1,
  "nikulas": 1,
  "kaluwa": 1,
  "sankalpa": 1,
  "thusithanjani": 1,
  "darshika": 1,
  "deshaja": 1,
  "premachandara": 1,
  "induka": 1,
  "karunapala": 1,
  "merian": 1,
  "askhan": 1,
  "thangalle": 1,
  "yaddehige": 1,
  "abharana": 1,
  "othara": 1,
  "diljiya": 1,
  "laveena": 1,
  "chandrapala": 1,
  "pannage": 1,
  "wimukthika": 1,
  "walakulu": 1,
  "nethmini": 1,
  "ruwansiri": 1,
  "amarasooriya": 1,
  "wevage": 1,
  "keerthisiri": 1,
  "dep": 1,
  "asuramana": 1,
  "imasha": 1,
  "kadiramaleege": 1,
  "madara": 1,
  "subair": 1,
  "kalhara": 1,
  "mukundadura": 1,
  "vidushika": 1,
  "kolindya": 1,
  "diana": 1,
  "pothupitiya": 1,
  "kasadoruge": 1,
  "kanushki": 1,
  "wickramarachchi": 1,
  "degiri": 1,
  "kularaja": 1,
  "kulasinghe": 1,
  "susima": 1,
  "hewawedage": 1,
  "adhipathige": 1,
  "sharli": 1,
  "prema": 1,
  "majuwana": 1,
  "medage": 1,
  "piyathilaka": 1,
  "randiran": 1,
  "prijet": 1,
  "rogusge": 1,
  "jinanthi": 1,
  "dalsi": 1,
  "stanis": 1,
  "vass": 1,
  "pavithra": 1,
  "ovitagedara": 1,
  "iromi": 1,
  "arachchila": 1,
  "ivosha": 1,
  "selvarani": 1,
  "rupika": 1,
  "suvini": 1,
  "sein": 1,
  "pestheruwe": 1,
  "maxwarld": 1,
  "wijewarnasooriya": 1,
  "dannangoda": 1,
  "samankumara": 1,
  "dilhara": 1,
  "jeyanandasing": 1,
  "kokilanathsing": 1,
  "dombagaha": 1,
  "shayuru": 1,
  "kisan": 1,
  "jiwanthika": 1,
  "puthra": 1,
  "alvis": 1,
  "peterge": 1,
  "wellamurage": 1,
  "human": 1,
  "wijesena": 1,
  "samansiri": 1,
  "sumana": 1,
  "nishani": 1,
  "niwarthana": 1,
  "urakaduge": 1,
  "ishraf": 1,
  "jawath": 1,
  "chameera": 1,
  "patabadhige": 1,
  "dagli": 1,
  "witharamalage": 1,
  "ishen": 1,
  "sarindu": 1,
  "nammuni": 1,
  "hamige": 1,
  "amarabandu": 1,
  "kappetipola": 1,
  "paskorale": 1,
  "nuwarapaksha": 1,
  "gunadasa": 1,
  "kahamgam": 1,
  "padmalal": 1,
  "pilippan": 1,
  "ge": 1,
  "rannulu": 1,
  "vikum": 1,
  "dewapriya": 1,
  "joshep": 1,
  "miranduge": 1,
  "vilmant": 1,
  "peri": 1,
  "pamburugamu": 1,
  "mahaarachchilage": 1,
  "somaweera": 1,
  "bothalage": 1,
  "lavos": 1,
  "nadhuni": 1,
  "diwyanjali": 1,
  "umayanga": 1,
  "muyin": 1,
  "lathif": 1,
  "yakoob": 1,
  "bowathanthri": 1,
  "pamudi": 1,
  "sajeevi": 1,
  "eliyadura": 1,
  "yohan": 1,
  "asurappulige": 1,
  "karunananda": 1,
  "indrawansha": 1,
  "mathota": 1,
  "hakahinna": 1,
  "pathirathna": 1,
  "agampodi": 1,
  "benthara": 1,
  "chance": 1,
  "premani": 1,
  "supurna": 1,
  "madhurangi": 1,
  "liyan": 1,
  "mayuranath": 1,
  "jeewapriya": 1,
  "ranawaka": 1,
  "dital": 1,
  "singarakkara": 1,
  "piyawathy": 1,
  "soorasinghe": 1,
  "thewarapperuma": 1,
  "raseni": 1,
  "weerakkutti": 1,
  "albenthulage": 1,
  "poornima": 1,
  "udayakanthi": 1,
  "hadara": 1,
  "amarasiri": 1,
  "kalutara": 1,
  "kundalabharana": 1,
  "gamachchilage": 1,
  "weerathunga": 1,
  "shiromala": 1,
  "bernard": 1,
  "gampala": 1,
  "jesica": 1,
  "rasanganee": 1,
  "jothirathna": 1,
  "sinthiya": 1,
  "olupathage": 1,
  "hiruni": 1,
  "pera": 1,
  "peramanna": 1,
  "pussalamankada": 1,
  "gregory": 1,
  "hemajith": 1,
  "dehiwala": 1,
  "emel": 1,
  "gangabadage": 1,
  "neelangani": 1,
  "sankha": 1,
  "viraj": 1,
  "jayawila": 1,
  "narangoda": 1,
  "pahalaralalage": 1,
  "ruvaitha": 1,
  "pingamage": 1,
  "dalsan": 1,
  "wedage": 1,
  "rasanjali": 1,
  "galhenage": 1,
  "jerry": 1,
  "vandot": 1,
  "suddanage": 1,
  "thudugalage": 1,
  "jeevani": 1,
  "priyanjaya": 1,
  "idippuli": 1,
  "philicia": 1,
  "trevo": 1,
  "kapuru": 1,
  "prasadinee": 1,
  "jayangani": 1,
  "rajamuni": 1,
  "susehewage": 1,
  "prasangi": 1,
  "vadivellage": 1,
  "wimalaweera": 1,
  "deliya": 1,
  "pilamin": 1,
  "patricia": 1,
  "imalda": 1,
  "welandame": 1,
  "aabitha": 1,
  "teshan": 1,
  "geekiyanage": 1,
  "pereralage": 1,
  "prithika": 1,
  "texila": 1,
  "madhusansa": 1,
  "vishwa": 1,
  "sulakshana": 1,
  "muththunayake": 1,
  "magdan": 1,
  "pol": 1,
  "gamagedara": 1,
  "pradip": 1,
  "anuja": 1,
  "nimantha": 1,
  "kasirajan": 1,
  "mirihana": 1,
  "abeysena": 1,
  "ponnam": 1,
  "perumage": 1,
  "filomina": 1,
  "catharin": 1,
  "hevage": 1,
  "sethunga": 1,
  "agnus": 1,
  "sathis": 1,
  "princi": 1,
  "lucida": 1,
  "manojith": 1,
  "bernet": 1,
  "benildus": 1,
  "weliweriya": 1,
  "mirisage": 1,
  "talahiti": 1,
  "liyavuruge": 1,
  "balagngnya": 1,
  "teslin": 1,
  "labroy": 1,
  "kekuluthotage": 1,
  "niraj": 1,
  "hettihewage": 1,
  "viyani": 1,
  "dorin": 1,
  "hemasiri": 1,
  "kahathuduge": 1,
  "dayawansa": 1,
  "shakila": 1,
  "eureka": 1,
  "geethanjana": 1,
  "colombo": 1,
  "vindya": 1,
  "shyamika": 1,
  "durage": 1,
  "battepolage": 1,
  "sekara": 1,
  "de-alwis": 1,
  "jayathunga": 1,
  "vijan": 1,
  "chandrappulige": 1,
  "devinda": 1,
  "saramge": 1,
  "osman": 1,
  "mahaguruge": 1,
  "deemal": 1,
  "robin": 1,
  "virani": 1,
  "shammi": 1,
  "wagage": 1,
  "madheera": 1,
  "paththinikuttige": 1,
  "lusion": 1,
  "geronius": 1,
  "wannigamage": 1,
  "gonkarage": 1,
  "raneesa": 1,
  "ishari": 1,
  "dinal": 1,
  "munihath": 1,
  "fedrick": 1,
  "kandanhena": 1,
  "kandulagedara": 1,
  "sirisoma": 1,
  "aqeel": 1,
  "sajiwani": 1,
  "ganganath": 1,
  "idame": 1,
  "andarage": 1,
  "wickramasekara": 1,
  "muthalike": 1,
  "gnanendra": 1,
  "of": 1,
  "dikelle": 1,
  "udayakumara": 1,
  "mallikarathna": 1,
  "appukutti": 1,
  "reeza": 1,
  "nifras": 1,
  "kerunna": 1,
  "tenison": 1,
  "samaraweera": 1,
  "makawitage": 1,
  "mahasen": 1,
  "leo": 1,
  "herbert": 1,
  "commitige": 1,
  "eric": 1,
  "laksiri": 1,
  "kalthota": 1,
  "gurunaithelage": 1,
  "nilan": 1,
  "harindra": 1,
  "chrisantha": 1,
  "ellenrose": 1,
  "makshim": 1,
  "kamalsiri": 1,
  "ignation": 1,
  "mahage": 1,
  "iruka": 1,
  "arsli": 1,
  "heva": 1,
  "janath": 1,
  "oshadi": 1,
  "leethiya": 1,
  "soththige": 1,
  "thenahandi": 1,
  "uhan": 1,
  "yaddessalage": 1,
  "dela": 1,
  "kehel": 1,
  "obadhage": 1,
  "rumen": 1,
  "mulavariyalage": 1,
  "nungamu": 1,
  "indrachapa": 1,
  "chandrawansha": 1,
  "anrani": 1,
  "poojika": 1,
  "hewasundara": 1,
  "rudrigulage": 1,
  "wickramarathna": 1,
  "neranjana": 1,
  "sitha": 1,
  "wishwajith": 1,
  "gurunnanselage": 1,
  "erandathi": 1,
  "attanayake": 1,
  "pamoda": 1,
  "yodha": 1,
  "githmi": 1,
  "gerald": 1,
  "mallawaarachchi": 1,
  "nanob": 1,
  "calistus": 1,
  "dhammikalal": 1,
  "vaila": 1,
  "kunjimama": 1,
  "wasington": 1,
  "yamange": 1,
  "tekla": 1,
  "handunneththi": 1,
  "handunpurage": 1,
  "imesh": 1,
  "kaludewage": 1,
  "kolambage": 1,
  "shashi": 1,
  "wijegunasena": 1,
  "loordu": 1,
  "oliver": 1,
  "eustus": 1,
  "naranapiti": 1,
  "paththage": 1,
  "lihini": 1,
  "prabhashani": 1,
  "singappuli": 1,
  "malaka": 1,
  "ahangama": 1,
  "ritani": 1,
  "malshan": 1,
  "kelmi": 1,
  "sriyanga": 1,
  "sheril": 1,
  "madhusanjana": 1,
  "rexita": 1,
  "sulani": 1,
  "tiron": 1,
  "arawe": 1,
  "kalinga": 1,
  "kotta": 1,
  "suranji": 1,
  "sembu": 1,
  "godwin": 1,
  "titus": 1,
  "elise": 1,
  "jenany": 1,
  "obris": 1,
  "jasintha": 1,
  "lazarus": 1,
  "vanderlen": 1,
  "fill": 1,
  "benadic": 1,
  "martin": 1,
  "leonard": 1,
  "deemas": 1,
  "sani": 1,
  "thotawaththage": 1,
  "herman": 1,
  "claude": 1,
  "will": 1,
  "helm": 1,
  "udawela": 1,
  "ranpatidewa": 1,
  "brahmana": 1,
  "jinendra": 1,
  "ralahamilage": 1,
  "sembukutty": 1,
  "wasthugedara": 1,
  "dulanjana": 1,
  "winton": 1,
  "ignasious": 1,
  "preethi": 1,
  "karunakaran": 1,
  "ingrit": 1,
  "devaka": 1,
  "hathurusinghe": 1,
  "ilesingha": 1,
  "prageeth": 1,
  "dharmajewa": 1,
  "polpitiye": 1,
  "rupananda": 1,
  "rajawansakkara": 1,
  "naduge": 1,
  "wannakuwaththa": 1,
  "gunawansha": 1,
  "deekirikewage": 1,
  "oska": 1,
  "arawwalage": 1,
  "inanda": 1,
  "shorin": 1,
  "wanigasekara": 1,
  "katukoliya": 1,
  "kamalawathi": 1,
  "lorage": 1,
  "jayaranga": 1,
  "ruwanari": 1,
  "colombage": 1,
  "angela": 1,
  "sheron": 1,
  "tharanganee": 1,
  "basil": 1,
  "polgaswatta": 1,
  "pallebhage": 1,
  "tensin": 1,
  "shamala": 1,
  "venuja": 1,
  "sattadi": 1,
  "bernadeth": 1,
  "renfeed": 1,
  "savin": 1,
  "lakith": 1,
  "master": 1,
  "indunil": 1,
  "brayantha": 1,
  "jeewantha": 1,
  "weedagama": 1,
  "ramya": 1,
  "nadisha": 1,
  "shiranga": 1,
  "sesappara": 1,
  "kaluarachchillage": 1,
  "waddayalage": 1,
  "samarajeewa": 1,
  "prashantha": 1,
  "govinda": 1,
  "bulathwelage": 1,
  "badra": 1,
  "shiromi": 1,
  "voshan": 1,
  "maxium": 1,
  "wikckramage": 1,
  "nilwala": 1,
  "fernandopulle": 1,
  "sithija": 1,
  "mihisara": 1,
  "disanayakalage": 1,
  "cletus": 1,
  "rona": 1,
  "ivedni": 1,
  "shirantha": 1,
  "shiroman": 1,
  "wadumesthrige": 1,
  "sembukuttige": 1,
  "lucian": 1,
  "seekku": 1,
  "baptist": 1,
  "shyam": 1
}