{
  "rathnayaka": 182,
  "dissanayaka": 182,
  "herath": 55,
  "rajapaksha": 54,
  "konara": 52,
  "aththanayaka": 31,
  "weerasinghe": 28,
  "jayasundara": 27,
  "jayasinghe": 27,
  "ranasinghe": 24,
  "wickramasinghe": 19,
  "jayawardhana": 18,
  "gunarathna": 17,
  "amarasinghe": 17,
  "karunarathna": 15,
  "jayalath": 13,
  "jayarathna": 12,
  "jayasekara": 11,
  "wijesinghe": 11,
  "adhikari": 11,
  "munasinghe": 11,
  "perera": 10,
  "wijerathna": 9,
  "basnayaka": 8,
  "samarakoon": 8,
  "hetti": 6,
  "dewage": 6,
  "thilakarathna": 6,
  "kodithuwakku": 6,
  "nanayakkara": 5,
  "kariyawasam": 5,
  "hennadige": 5,
  "bandage": 5,
  "thennakoon": 5,
  "senarathna": 4,
  "warnakulasooriya": 4,
  "abeykoon": 4,
  "jayakodi": 3,
  "rasaiya": 3,
  "fernando": 3,
  "appuhami": 2,
  "pathirannehelage": 2,
  "tharmalingam": 2,
  "ganeshan": 2,
  "kandaiya": 2,
  "selvarasa": 2,
  "ekanayaka": 2,
  "de-silva": 2,
  "rajarathnam": 2,
  "chandrasekara": 2,
  "chandrakumar": 2,
  "kajenthiran": 1,
  "hameed": 1,
  "aliyar": 1,
  "musthafa": 1,
  "sellathurai": 1,
  "rajkumar": 1,
  "ihala": 1,
  "subramaniyam": 1,
  "thangavel": 1,
  "shanmuganathan": 1,
  "mahalingam": 1,
  "vijayakumar": 1,
  "dewa": 1,
  "sinnaiya": 1,
  "silva": 1
}